LICENSE
README.md
setup.cfg
setup.py
iammeterWpc/__init__.py
iammeterWpc/api.py
iammeterWpc/example.py
iammeterWpc.egg-info/PKG-INFO
iammeterWpc.egg-info/SOURCES.txt
iammeterWpc.egg-info/dependency_links.txt
iammeterWpc.egg-info/top_level.txt