Metadata-Version: 2.1
Name: iammeterWpc
Version: 0.1
Summary: IamMeterWpc api
Home-page: https://github.com/yangbo1979/iammeter_wpc_pip_lib
Author: yangbo1979
Author-email: gyangbo@gmail.com
License: UNKNOWN
Platform: UNKNOWN
Classifier: Programming Language :: Python :: 3
Classifier: License :: OSI Approved :: MIT License
Classifier: Operating System :: OS Independent
